heospy/__init__.py
heospy/__main__.py
heospy/_version.py
heospy/ssdp.py
heospy-0.2.7.dist-info/LICENSE.txt
heospy-0.2.7.dist-info/METADATA
heospy-0.2.7.dist-info/WHEEL
heospy-0.2.7.dist-info/entry_points.txt
heospy-0.2.7.dist-info/top_level.txt
heospy-0.2.7.dist-info/RECORD
