Metadata-Version: 2.1
Name: heospy
Version: 0.2.7
Summary: Control an HEOS player with a Python script
Home-page: https://github.com/ping13/heospy
Author: Stephan Heuel
Author-email: mail@ping13.net
License: UNKNOWN
Project-URL: Bug Tracker, https://github.com/ping13/heospy/issues
Keywords: api,heos,marantz,denon,audio
Platform: UNKNOWN
Classifier: Programming Language :: Python :: 3
Classifier: License :: OSI Approved :: MIT License
Classifier: Operating System :: OS Independent
License-File: LICENSE.txt
Requires-Dist: six
Requires-Dist: future
